ezlambda/__init__.py
ezlambda/variable.py
ezlambda-0.1.2.dist-info/LICENSE
ezlambda-0.1.2.dist-info/METADATA
ezlambda-0.1.2.dist-info/WHEEL
ezlambda-0.1.2.dist-info/top_level.txt
ezlambda-0.1.2.dist-info/RECORD
