Metadata-Version: 2.1
Name: ezlambda
Version: 0.1.2
Summary: Easy and intuitive notation to replace simple lambda functions.
Author: adesanjo
License: MIT License        
Project-URL: Homepage, https://github.com/adesanjo/ezlambda
Keywords: ez,lambda,easy,easylambda,function,functional,ezlambda
Classifier: License :: OSI Approved :: MIT License
Classifier: Programming Language :: Python
Classifier: Programming Language :: Python :: 3
Requires-Python: >=3.10
License-File: LICENSE
Provides-Extra: dev
